firehole/__init__.py
firehole/exception.py
firehole/algorithms/__init__.py
firehole/algorithms/weight.py
firehole/algorithms/ahp/__init__.py
firehole/algorithms/ahp/__main__.py
firehole/algorithms/ahp/errors.py
firehole/algorithms/ahp/parser.py
firehole/algorithms/ahp/utils.py
firehole/algorithms/ahp/hierarchy/__init__.py
firehole/algorithms/ahp/hierarchy/ahpcriterion.py
firehole/algorithms/ahp/hierarchy/ahpmodel.py
firehole/algorithms/ahp/methods/__init__.py
firehole/algorithms/ahp/methods/approximate.py
firehole/algorithms/ahp/methods/eigenvalue.py
firehole/algorithms/ahp/methods/geometric.py
firehole/algorithms/ahp/methods/method.py
firehole/algorithms/convert/__init__.py
firehole/algorithms/convert/convertID.py
firehole/algorithms/flashtext/__init__.py
firehole/algorithms/flashtext/keyword.py
firehole/algorithms/similarity/__init__.py
firehole/algorithms/similarity/rank_bm25.py
firehole/algorithms/similarity/simhash.py
firehole-0.4.2.dist-info/LICENSE
firehole-0.4.2.dist-info/METADATA
firehole-0.4.2.dist-info/WHEEL
firehole-0.4.2.dist-info/top_level.txt
firehole-0.4.2.dist-info/RECORD
