Metadata-Version: 2.1
Name: firehole
Version: 0.4.2
Summary: FireHole (fh) is a Python package for Data Analyst.
Home-page: https://github.com/xSumner/firehole
Author: Xia Tian
Author-email: xsumner@hotmail.com
License: UNKNOWN
Keywords: Data Analysis,AHP
Platform: UNKNOWN
Requires-Python: >=3
Requires-Dist: numpy (>=1.13.0)
Requires-Dist: scipy (>=1.0.0)
